mongodata/__init__.py
mongodata/cache.py
mongodata/client.py
mongodata/cursor.py
mongodata-0.2.1.dist-info/LICENSE
mongodata-0.2.1.dist-info/METADATA
mongodata-0.2.1.dist-info/WHEEL
mongodata-0.2.1.dist-info/top_level.txt
mongodata-0.2.1.dist-info/RECORD
