Metadata-Version: 2.1
Name: mongodata
Version: 0.2.1
Summary: A basic ORM like interface for mongodb in python.
Author-email: José Antonio Puértolas Montañés <63794670+j5pu@users.noreply.github.com>
License: MIT
Project-URL: Homepage, https://github.com/j5pu/mongodata
Requires-Python: >=3.11
License-File: LICENSE
Requires-Dist: dnspython <3,>=2.2.1
Requires-Dist: furl <3,>=2.1.3
Requires-Dist: huti <1,>=0.1.15
Requires-Dist: mongita <2,>=1.1.1
Requires-Dist: nodeps[pretty]
Requires-Dist: pymongo <5,>=4.5.0
Requires-Dist: redis <6,>=5.0.0
Requires-Dist: requests <3,>=2.31.0
Provides-Extra: dev
Requires-Dist: nodeps[all,dev] ; extra == 'dev'
